httomolib/__init__.py
httomolib/misc/DejaVuSans.ttf
httomolib/misc/__init__.py
httomolib/misc/images.py
httomolib/misc/morph.py
httomolib/misc/segm.py
httomolib/prep/__init__.py
httomolib/prep/phase.py
httomolib-2.2.dist-info/LICENSE
httomolib-2.2.dist-info/METADATA
httomolib-2.2.dist-info/WHEEL
httomolib-2.2.dist-info/top_level.txt
httomolib-2.2.dist-info/RECORD
