Metadata-Version: 2.1
Name: httomolib
Version: 2.2
Summary: Commonly used tomography data processing methods at DLS.
Author-email: Daniil Kazantsev <daniil.kazantsev@diamond.ac.uk>, Yousef Moazzam <yousef.moazzam@diamond.ac.uk>, Naman Gera <naman.gera@diamond.ac.uk>
License: BSD-3-Clause
Project-URL: Repository, https://github.com/DiamondLightSource/httomolib
Classifier: Development Status :: 4 - Beta
Classifier: License :: OSI Approved :: BSD License
Classifier: Programming Language :: Python :: 3.10
Requires-Python: >=3.10
License-File: LICENSE
Requires-Dist: numpy
Requires-Dist: scipy
Requires-Dist: pillow
Requires-Dist: scikit-image
Requires-Dist: aiofiles
Provides-Extra: dev
Requires-Dist: pytest; extra == "dev"
Requires-Dist: pytest-cov; extra == "dev"
Requires-Dist: pytest-xdist; extra == "dev"
Requires-Dist: flake8; extra == "dev"
Requires-Dist: pyproject-flake8; extra == "dev"
Requires-Dist: pydocstyle; extra == "dev"
Requires-Dist: toml; extra == "dev"
Requires-Dist: imageio; extra == "dev"
Requires-Dist: setuptools-git-versioning; extra == "dev"
